tokko_permission_tools/__init__.py
tokko_permission_tools/cli.py
tokko_permission_tools/client.py
tokko_permission_tools/templates.py
tokko_permission_tools/tests.py
tokko_permission_tools/utils.py
tokko_permission_tools/api/__init__.py
tokko_permission_tools/api/common.py
tokko_permission_tools/api/permission.py
tokko_permission_tools/api/users.py
tokko_permission_tools-0.0.1.dist-info/METADATA
tokko_permission_tools-0.0.1.dist-info/WHEEL
tokko_permission_tools-0.0.1.dist-info/entry_points.txt
tokko_permission_tools-0.0.1.dist-info/top_level.txt
tokko_permission_tools-0.0.1.dist-info/RECORD
