Metadata-Version: 2.1
Name: tokko-permission-tools
Version: 0.0.1
Summary: Tokko Permission Tools
Home-page: https://github.com/TokkoLabs/auth-plugins/tokko-auth-core.git
Author: Jose Salgado
Author-email: jsalgado@navent.com
License: BSD License
Platform: UNKNOWN
Classifier: Intended Audience :: Developers
Classifier: License :: OSI Approved :: BSD License
Classifier: Operating System :: OS Independent
Classifier: Programming Language :: Python
Classifier: Programming Language :: Python :: 3.8
Classifier: Topic :: Internet :: WWW/HTTP
Classifier: Topic :: Internet :: WWW/HTTP :: Dynamic Content
Requires-Dist: click (==7.1.2)
Requires-Dist: jinja2
